gasthermo/__init__.py
gasthermo/cp.py
gasthermo/cp_ig.csv
gasthermo/critical_constants.csv
gasthermo/critical_constants.py
gasthermo/thermal_conductivity.py
gasthermo/viscosity.py
gasthermo-0.0.6.dist-info/LICENSE
gasthermo-0.0.6.dist-info/METADATA
gasthermo-0.0.6.dist-info/WHEEL
gasthermo-0.0.6.dist-info/top_level.txt
gasthermo-0.0.6.dist-info/RECORD
