Metadata-Version: 2.1
Name: gasthermo
Version: 0.0.6
Summary: Gas-Phase Thermodynamics in Python
Home-page: https://github.com/dejac001/GasThermo
Author: Robert F. De Jaco
Author-email: dejac001@umn.edu
License: UNKNOWN
Platform: UNKNOWN
Classifier: Programming Language :: Python :: 3
Classifier: License :: OSI Approved :: GNU Lesser General Public License v3 (LGPLv3)
Classifier: Operating System :: OS Independent
Requires-Python: >=3.6
Requires-Dist: matplotlib (==3.2.1)
Requires-Dist: numpy (==1.18.4)
Requires-Dist: scipy (==1.4.1)
Requires-Dist: chem-util (==0.0.4)
